peh_model/__init__.py
peh_model/peh.py
peh_model/pydanticmodel_v2.py
peh_model/typed.py
peh_model/schema/peh.yaml
peh_model-0.2.0.dist-info/METADATA
peh_model-0.2.0.dist-info/WHEEL
peh_model-0.2.0.dist-info/top_level.txt
peh_model-0.2.0.dist-info/RECORD
