Metadata-Version: 2.4
Name: peh-model
Version: 0.2.0
Summary: Python package for the PEH data model.
Author-email: Dirk Devriendt <dirk.devriendt.ext@vito.be>, Gertjan Bisschop <gertjan.bisschop@vito.be>
License: MIT
Project-URL: Homepage, https://github.com/eu-parc/parco-hbm
Project-URL: Bug Tracker, https://github.com/eu-parc/parco-hbm/issues
Classifier: Programming Language :: Python :: 3
Classifier: License :: OSI Approved :: MIT License
Classifier: Operating System :: OS Independent
Requires-Python: >=3.10
Requires-Dist: pydantic>=2.0.0
Requires-Dist: linkml-runtime
Provides-Extra: docs
Requires-Dist: linkml; extra == "docs"
Requires-Dist: mkdocs; extra == "docs"
Requires-Dist: mkdocs-material>=8.2.8; extra == "docs"
Requires-Dist: mkdocs-mermaid2-plugin>=1.1.1; extra == "docs"
Requires-Dist: mknotebooks>=0.8.0; extra == "docs"
